joby_m_anthony_iii/__init__.py
joby_m_anthony_iii/numerical_methods.py
joby_m_anthony_iii/truncate_file.py
joby_m_anthonyiii/__init__.py
joby_m_anthonyiii/numerical_methods.py
joby_m_anthony_iii-1.4.9.dist-info/LICENSE
joby_m_anthony_iii-1.4.9.dist-info/METADATA
joby_m_anthony_iii-1.4.9.dist-info/WHEEL
joby_m_anthony_iii-1.4.9.dist-info/top_level.txt
joby_m_anthony_iii-1.4.9.dist-info/RECORD
